Topsis_102017172_Mannat/102017172.py
Topsis_102017172_Mannat/__init__.py
Topsis_102017172_Mannat-0.0.1.dist-info/LICENSE
Topsis_102017172_Mannat-0.0.1.dist-info/METADATA
Topsis_102017172_Mannat-0.0.1.dist-info/WHEEL
Topsis_102017172_Mannat-0.0.1.dist-info/top_level.txt
Topsis_102017172_Mannat-0.0.1.dist-info/RECORD
