Metadata-Version: 2.1
Name: Topsis-102017172-Mannat
Version: 0.0.1
Summary: Topsis score calculator
Home-page: https://github.com/Mannat7/Topsis_102017172
Author: Mannat
Author-email: Mannat <mannat7873@gmail.com>
License: MIT
Project-URL: Homepage, https://github.com/Mannat7/Topsis_102017172
Keywords: topsis,rank,topsis score
Classifier: Programming Language :: Python :: 3
Classifier: License :: OSI Approved :: MIT License
Classifier: Operating System :: OS Independent
Requires-Python: >=3.7
License-File: LICENSE
Requires-Dist: pandas
